ki2_python_utils/FlowBuffer.py
ki2_python_utils/__init__.py
ki2_python_utils/async_utils.py
ki2_python_utils/exist.py
ki2_python_utils/filter.py
ki2_python_utils/json.py
ki2_python_utils/list_utils.py
ki2_python_utils/py.typed
ki2_python_utils-0.3.5.dist-info/LICENSE.md
ki2_python_utils-0.3.5.dist-info/METADATA
ki2_python_utils-0.3.5.dist-info/WHEEL
ki2_python_utils-0.3.5.dist-info/RECORD
