Metadata-Version: 2.1
Name: ki2-python-utils
Version: 0.3.5
Summary: A small library providing utility classes and functions to simplify common Python tasks like handling lists, JSON, and asynchronous workflows.
License: MIT
Author: Adrien KERFOURN
Author-email: ak.sitecontact@gmail.com
Requires-Python: >=3.10,<4.0
Classifier: License :: OSI Approved :: MIT License
Classifier: Programming Language :: Python :: 3
Classifier: Programming Language :: Python :: 3.10
Classifier: Programming Language :: Python :: 3.11
Classifier: Programming Language :: Python :: 3.12
Classifier: Programming Language :: Python :: 3.13
Requires-Dist: typing-extensions (>=4.12.2,<5.0.0)
